coffee_dou_ui_py/__init__.py
coffee_dou_ui_py/coffee_dou_ui_py.py
coffee_dou_ui_py-0.0.2.dist-info/LICENSE
coffee_dou_ui_py-0.0.2.dist-info/METADATA
coffee_dou_ui_py-0.0.2.dist-info/WHEEL
coffee_dou_ui_py-0.0.2.dist-info/top_level.txt
coffee_dou_ui_py-0.0.2.dist-info/RECORD
